example/__init__.py
example/manage.py
example/dj/__init__.py
example/dj/urls.py
example/dj/wsgi.py
example/dj/apps/__init__.py
example/dj/apps/app/__init__.py
example/dj/apps/app/models.py
example/dj/apps/app/tests/__init__.py
example/dj/apps/app/tests/base.py
example/dj/apps/app/tests/commands.py
example/dj/apps/app/tests/models.py
example/dj/settings/__init__.py
example/dj/settings/base.py
example/dj/settings/settings.py
verification_token/__init__.py
verification_token/config.py
verification_token/generators.py
verification_token/models.py
verification_token/version.py
verification_token/management/__init__.py
verification_token/management/commands/__init__.py
verification_token/management/commands/clean_verification_tokens.py
verification_token/migrations/0001_initial.py
verification_token/migrations/0002.py
verification_token/migrations/0003_migration.py
verification_token/migrations/0004_migration.py
verification_token/migrations/0005_migration.py
verification_token/migrations/__init__.py
skip_django_verification_token-0.0.8.1.dist-info/LICENSE
skip_django_verification_token-0.0.8.1.dist-info/METADATA
skip_django_verification_token-0.0.8.1.dist-info/WHEEL
skip_django_verification_token-0.0.8.1.dist-info/top_level.txt
skip_django_verification_token-0.0.8.1.dist-info/RECORD
