Metadata-Version: 2.1
Name: skip-django-verification-token
Version: 0.0.8.1
Summary: Django library for generation verification toekens.
Home-page: https://github.com/skip-pay/django-verification-token
Author: Lubos Matl
Author-email: matllubos@gmail.com
License: BSD
Keywords: django,verification token
Classifier: Development Status :: 3 - Alpha
Classifier: Framework :: Django
Classifier: Intended Audience :: Developers
Classifier: License :: OSI Approved :: BSD License
Classifier: Operating System :: OS Independent
Classifier: Programming Language :: Python
Classifier: Topic :: Internet :: WWW/HTTP
License-File: LICENSE
Requires-Dist: django (>=2.2)
